pipim.py
pipim-1.2.0.dist-info/LICENSE
pipim-1.2.0.dist-info/METADATA
pipim-1.2.0.dist-info/WHEEL
pipim-1.2.0.dist-info/entry_points.txt
pipim-1.2.0.dist-info/top_level.txt
pipim-1.2.0.dist-info/RECORD
