Metadata-Version: 2.1
Name: pipim
Version: 1.2.0
Summary: A drop-in replacement for pip
Home-page: https://github.com/Tina-otoge/pip-improved
Author: Tina
License-File: LICENSE
